README.rst
setup.py
django_podcast_feed_py2.egg-info/PKG-INFO
django_podcast_feed_py2.egg-info/SOURCES.txt
django_podcast_feed_py2.egg-info/dependency_links.txt
django_podcast_feed_py2.egg-info/requires.txt
django_podcast_feed_py2.egg-info/top_level.txt
podcast_feed/__init__.py
podcast_feed/podcast.py