Metadata-Version: 1.1
Name: django-podcast-feed-py2
Version: 0.0.3
Summary: Generate Apple Podcasts-compatible syndication feeds.
Home-page: https://github.com/jeffbr13/xq
Author: Ben Jeffrey
Author-email: mail@benjeffrey.net
License: MPL 2.0
Keywords: django podcast feed
Platform: UNKNOWN
Classifier: Development Status :: 3 - Alpha
Classifier: Programming Language :: Python :: 2
Classifier: Intended Audience :: Developers
Classifier: License :: OSI Approved :: Mozilla Public License 2.0 (MPL 2.0)
Classifier: Framework :: Django
